pordego/__init__.py
pordego/cli.py
pordego/config_loader.py
pordego/discovery.py
pordego/junit_output.py
pordego/logging_output.py
pordego/main.py
pordego/plugin_logging.py
pordego-1.2.1.dist-info/DESCRIPTION.rst
pordego-1.2.1.dist-info/METADATA
pordego-1.2.1.dist-info/RECORD
pordego-1.2.1.dist-info/WHEEL
pordego-1.2.1.dist-info/entry_points.txt
pordego-1.2.1.dist-info/metadata.json
pordego-1.2.1.dist-info/top_level.txt
