Metadata-Version: 2.0
Name: pordego
Version: 1.2.1
Summary: Command line tool for running configurable static analysis plugins on Python code
Home-page: https://github.com/ttreptow/pordego
Author: Tim Treptow
Author-email: tim.treptow@gmail.com
License: UNKNOWN
Download-URL: https://github.com/ttreptow/pordego/tarball/1.2.1
Platform: UNKNOWN
Classifier: Development Status :: 4 - Beta
Classifier: Intended Audience :: Developers
Classifier: License :: OSI Approved :: MIT License
Classifier: Operating System :: OS Independent
Classifier: Programming Language :: Python
Classifier: Programming Language :: Python :: 2.7
Requires-Dist: junit-xml
Requires-Dist: pyyaml
